{"name":"zls","metrics":{"start_time":1690962723615,"completion_time":1690962724467},"links":{"share":{"mason-schemas\\lsp\\zls.json":"mason-schemas\\lsp.json"},"bin":{"zls.cmd":"bin\/zls.exe"},"opt":{}},"primary_source":{"source":{"repo":"zigtools\/zls","downloads":[{"out_file":"x86_64-windows.tar.zst","download_url":"https:\/\/github.com\/zigtools\/zls\/releases\/download\/0.10.0\/x86_64-windows.tar.zst"}],"asset":{"file":"x86_64-windows.tar.zst","bin":"bin\/zls.exe","target":"win_x64"}},"type":"registry+v1","id":"pkg:github\/zigtools\/zls@0.10.0"},"secondary_sources":[],"schema_version":"1.1"}